Workbook

Sheet Cover
A1: DCF Valuation Model - CISCO SYSTEMS, INC. (CSCO)
A3: Prepared For: Investment Banking Associates
A4: Prepared By: PitchCraftAI
A5: As of: February 3, 2026

Sheet Contents
A1: Model Contents
A3: Tab | B3: Purpose
A4: Cover | B4: Model cover
A5: Contents | B5: Table of contents
A6: Inputs_Index | B6: Key inputs and controls
A7: Key_Assumptions | B7: Core model assumptions
A8: Historical_IS | B8: Historical income statement
A9: Historical_BS | B9: Historical balance sheet
A10: Historical_CF | B10: Historical cash flow
A11: Revenue_Build | B11: Revenue forecast build
A12: COGS_Gross_Margin | B12: Gross margin / COGS build
A13: Opex | B13: Operating expenses
A14: EBITDA_Bridge | B14: EBITDA derivation
... A33: Charts_Checks | B33: Charts and error checks

Sheet Inputs_Index
A1: Inputs Index
A3: Input | B3: Value
A4: Base Revenue ($M) | B4: =Key_Assumptions!B8
A5: EBITDA Margin | B5: =Key_Assumptions!B16
A6: D&A (% Rev) | B6: =Key_Assumptions!B17
A7: Capex (% Rev) | B7: =Key_Assumptions!B18
A8: NWC (% Rev) | B8: =Key_Assumptions!B19
A9: Tax Rate | B9: =Key_Assumptions!B20
A10: WACC | B10: =WACC!B15
A11: Terminal Growth | B11: =Key_Assumptions!B37
A12: Exit EV/EBITDA | B12: =Key_Assumptions!B38
A13: Net Debt ($M) | B13: =Key_Assumptions!B41
A14: Shares (M) | B14: =Key_Assumptions!B42

Sheet Key_Assumptions
A1: Key Assumptions - CISCO SYSTEMS, INC. (CSCO)
A3: COMPANY INFORMATION
A4: Company Name | B4: CISCO SYSTEMS, INC.
A5: Ticker | B5: CSCO
A7: REVENUE ASSUMPTIONS
A8: Base Year Revenue ($M) | B8: 56998
A9: Year 1 Growth | B9: 0.022
A10: Year 2 Growth | B10: 0.02
A11: Year 3 Growth | B11: 0.016
A12: Year 4 Growth | B12: 0.012
A13: Year 5 Growth | B13: 0.01
A15: OPERATING ASSUMPTIONS
A16: EBITDA Margin | B16: 0.276
A17: D&A (% of Revenue) | B17: 0.04
A18: CapEx (% of Revenue) | B18: 0.05
A19: NWC (% of Revenue) | B19: 0.068493151
A20: Tax Rate | B20: 0.24
A22: WACC BUILDUP
A23: Risk-Free Rate | B23: 0.043
A24: Equity Risk Premium | B24: 0.055
A25: Unlevered Beta | B25: 1
A26: Levered Beta | B26: 1.19
A27: Size Premium | B27: 0.01
A28: Company Risk Premium | B28: 0.01
A29: Pre-Tax Cost of Debt | B29: 0.065
A30: Debt / Total Capital | B30: 0.2
A32: Cost of Equity (CAPM + Adj) | B32: =B23+B26*B24+B27+B28
A33: After-Tax Cost of Debt | B33: =B29*(1-B20)
A34: WACC | B34: =B32*(1-B30)+B33*B30
A36: TERMINAL VALUE ASSUMPTIONS
A37: Perpetuity Growth Rate | B37: 0.025
A38: Exit EV/EBITDA Multiple | B38: 12
A40: CAPITAL STRUCTURE
A41: Net Debt ($M) | B41: 16265
A42: Shares Outstanding (M) | B42: 4007
A44: MODEL SETTINGS
A45: Use Mid-Year Convention | B45: 1 | C45: (1=Yes, 0=No)

Sheet Historical_IS
A1: Historical IS
A3: (Populate with historical financials)

Sheet Historical_BS
A1: Historical BS
A3: (Populate with historical financials)

Sheet Historical_CF
A1: Historical CF
A3: (Populate with historical financials)

Sheet Revenue_Build
A1: Revenue Build
B3: Base | C3: Year 1 | D3: Year 2 | E3: Year 3 | F3: Year 4 | G3: Year 5
A4: Revenue Growth | B4: — | C4: =Key_Assumptions!B9 | D4: =Key_Assumptions!B10 | E4: =Key_Assumptions!B11 | F4: =Key_Assumptions!B12 | G4: =Key_Assumptions!B13
A5: Revenue | B5: =Key_Assumptions!B8 | C5: =B5*(1+C4) | D5: =C5*(1+D4) | E5: =D5*(1+E4) | F5: =E5*(1+F4) | G5: =F5*(1+G4)

Sheet COGS_Gross_Margin
A1: COGS & Gross Margin
A3: (Placeholder for COGS and gross margin build)

Sheet Opex
A1: Operating Expenses
A3: (Placeholder for opex build)

Sheet EBITDA_Bridge
A1: EBITDA Bridge
B3: Base | C3: Year 1 | D3: Year 2 | E3: Year 3 | F3: Year 4 | G3: Year 5
A4: Revenue | B4: =Revenue_Build!B5 | C4: =Revenue_Build!C5 | D4: =Revenue_Build!D5 | E4: =Revenue_Build!E5 | F4: =Revenue_Build!F5 | G4: =Revenue_Build!G5
A5: EBITDA Margin | B5: =Key_Assumptions!B16 | C5: =Key_Assumptions!B16 | D5: =Key_Assumptions!B16 | E5: =Key_Assumptions!B16 | F5: =Key_Assumptions!B16 | G5: =Key_Assumptions!B16
A6: EBITDA | B6: =B4*B5 | C6: =C4*C5 | D6: =D4*D5 | E6: =E4*E5 | F6: =F4*F5 | G6: =G4*G5

Sheet D&A
A1: Depreciation & Amortization
B3: Base | C3: Year 1 | D3: Year 2 | E3: Year 3 | F3: Year 4 | G3: Year 5
A4: D&A (% Rev) | B4: =Key_Assumptions!B17 | C4: =Key_Assumptions!B17 | D4: =Key_Assumptions!B17 | E4: =Key_Assumptions!B17 | F4: =Key_Assumptions!B17 | G4: =Key_Assumptions!B17
A5: D&A | B5: =-Revenue_Build!B5*B4 | C5: =-Revenue_Build!C5*C4 | D5: =-Revenue_Build!D5*D4 | E5: =-Revenue_Build!E5*E4 | F5: =-Revenue_Build!F5*F4 | G5: =-Revenue_Build!G5*G4

Sheet Capex
A1: Capital Expenditures
B3: Base | C3: Year 1 | D3: Year 2 | E3: Year 3 | F3: Year 4 | G3: Year 5
A4: Capex (% Rev) | B4: =Key_Assumptions!B18 | C4: =Key_Assumptions!B18 | D4: =Key_Assumptions!B18 | E4: =Key_Assumptions!B18 | F4: =Key_Assumptions!B18 | G4: =Key_Assumptions!B18
A5: Capex | B5: =-Revenue_Build!B5*B4 | C5: =-Revenue_Build!C5*C4 | D5: =-Revenue_Build!D5*D4 | E5: =-Revenue_Build!E5*E4 | F5: =-Revenue_Build!F5*F4 | G5: =-Revenue_Build!G5*G4

Sheet Working_Capital
A1: Working Capital
B3: Base | C3: Year 1 | D3: Year 2 | E3: Year 3 | F3: Year 4 | G3: Year 5
A4: NWC (% Rev) | B4: =Key_Assumptions!B19 | C4: =Key_Assumptions!B19 | D4: =Key_Assumptions!B19 | E4: =Key_Assumptions!B19 | F4: =Key_Assumptions!B19 | G4: =Key_Assumptions!B19
A5: Change in NWC | B5: 0 | C5: =-(C5-B5)*C4 | D5: =-(D5-C5)*D4 | E5: =-(E5-D5)*E4 | F5: =-(F5-E5)*F4 | G5: =-(G5-F5)*G4

Sheet Other_Operating
A1: Other Operating Items
A3: (Placeholder for other operating items)

Sheet Taxes
A1: Taxes
B3: Base | C3: Year 1 | D3: Year 2 | E3: Year 3 | F3: Year 4 | G3: Year 5
A4: EBIT | B4: =EBITDA_Bridge!B6+D&A!B5 | C4: =EBITDA_Bridge!C6+D&A!C5 | D4: =EBITDA_Bridge!D6+D&A!D5 | E4: =EBITDA_Bridge!E6+D&A!E5 | F4: =EBITDA_Bridge!F6+D&A!F5 | G4: =EBITDA_Bridge!G6+D&A!G5
A5: Tax Rate | B5: =Key_Assumptions!B20 | C5: =Key_Assumptions!B20 | D5: =Key_Assumptions!B20 | E5: =Key_Assumptions!B20 | F5: =Key_Assumptions!B20 | G5: =Key_Assumptions!B20
A6: Taxes | B6: =-MAX(0,B4)*B5 | C6: =-MAX(0,C4)*C5 | D6: =-MAX(0,D4)*D5 | E6: =-MAX(0,E4)*E5 | F6: =-MAX(0,F4)*F5 | G6: =-MAX(0,G4)*G5

Sheet Unlevered_FCF
A1: Unlevered Free Cash Flow
B3: Base | C3: Year 1 | D3: Year 2 | E3: Year 3 | F3: Year 4 | G3: Year 5
A4: EBIT | B4: =Taxes!B4 | C4: =Taxes!C4 | D4: =Taxes!D4 | E4: =Taxes!E4 | F4: =Taxes!F4 | G4: =Taxes!G4
A5: Less: Taxes | B5: =Taxes!B6 | C5: =Taxes!C6 | D5: =Taxes!D6 | E5: =Taxes!E6 | F5: =Taxes!F6 | G5: =Taxes!G6
A6: NOPAT | B6: =B4+B5 | C6: =C4+C5 | D6: =D4+D5 | E6: =E4+E5 | F6: =F4+F5 | G6: =G4+G5
A7: Plus: D&A | B7: =-D&A!B3 | C7: =-D&A!C3 | D7: =-D&A!D3 | E7: =-D&A!E3 | F7: =-D&A!F3 | G7: =-D&A!G3
A8: Less: Capex | B8: =Capex!B3 | C8: =Capex!C3 | D8: =Capex!D3 | E8: =Capex!E3 | F8: =Capex!F3 | G8: =Capex!G3
A9: Less: Change in NWC | B9: =Working_Capital!B3 | C9: =Working_Capital!C3 | D9: =Working_Capital!D3 | E9: =Working_Capital!E3 | F9: =Working_Capital!F3 | G9: =Working_Capital!G3
A10: Unlevered FCF | B10: =B6+B7+B8+B9 | C10: =C6+C7+C8+C9 | D10: =D6+D7+D8+D9 | E10: =E6+E7+E8+E9 | F10: =F6+F7+F8+F9 | G10: =G6+G7+G8+G9

Sheet Debt_Schedule
A1: Debt Schedule
A3: (Placeholder for debt schedule)

Sheet Interest_Expense
A1: Interest Expense
A3: (Placeholder for interest schedule)

Sheet Share_Count
A1: Share Count
A3: (Placeholder for share count schedule)

Sheet WACC
A1: WACC Build
A3: WACC BUILDUP
A4: Risk-Free Rate | B4: 0.043
A5: Equity Risk Premium | B5: 0.055
A6: Unlevered Beta | B6: 1
A7: Levered Beta | B7: 1.19
A8: Size Premium | B8: 0.01
A9: Company Risk Premium | B9: 0.01
A10: Pre-Tax Cost of Debt | B10: 0.065
A11: Debt / Total Capital | B11: 0.2
A13: Cost of Equity (CAPM + Adj) | B13: =B4+B7*B5+B8+B9
A14: After-Tax Cost of Debt | B14: =B10*(1-Key_Assumptions!B20)
A15: WACC | B15: =B13*(1-B11)+B14*B11

Sheet DCF_Valuation
A1: Discounted Cash Flow Valuation
B3: Base | C3: Year 1 | D3: Year 2 | E3: Year 3 | F3: Year 4 | G3: Year 5
A4: Unlevered FCF | B4: =Unlevered_FCF!B10 | C4: =Unlevered_FCF!C10 | D4: =Unlevered_FCF!D10 | E4: =Unlevered_FCF!E10 | F4: =Unlevered_FCF!F10 | G4: =Unlevered_FCF!G10
A6: PRESENT VALUE CALCULATION
A7: Discount Period | C7: =IF(Key_Assumptions!B45=1,0+0.5,1) | D7: =IF(Key_Assumptions!B45=1,1+0.5,2) | E7: =IF(Key_Assumptions!B45=1,2+0.5,3) | F7: =IF(Key_Assumptions!B45=1,3+0.5,4) | G7: =IF(Key_Assumptions!B45=1,4+0.5,5)
A8: Discount Factor | C8: =1/(1+WACC!B15)^C7 | D8: =1/(1+WACC!B15)^D7 | E8: =1/(1+WACC!B15)^E7 | F8: =1/(1+WACC!B15)^F7 | G8: =1/(1+WACC!B15)^G7
A9: PV of FCF | C9: =C3*C8 | D9: =D3*D8 | E9: =E3*E8 | F9: =F3*F8 | G9: =G3*G8
A11: VALUATION SUMMARY
A12: Sum of PV of FCFs | B12: =SUM(C9:G9)
A14: GORDON GROWTH METHOD
A15: Enterprise Value | B15: =B13+Terminal_Value!B5
A16: Less: Net Debt | B16: =-Key_Assumptions!B41
A17: Equity Value | B17: =B15+B16
A18: Implied Share Price | B18: =B17/Key_Assumptions!B42
A20: EXIT MULTIPLE METHOD
A21: Enterprise Value | B21: =B14+Terminal_Value!B6
A22: Less: Net Debt | B22: =-Key_Assumptions!B41
A23: Equity Value | B23: =B21+B22
A24: Implied Share Price | B24: =B23/Key_Assumptions!B42

Sheet Terminal_Value
A1: Terminal Value
A3: Terminal Value (Gordon Growth) | B3: =Unlevered_FCF!G10*(1+Key_Assumptions!B37)/(WACC!B15-Key_Assumptions!B37)
A4: Terminal Value (Exit Multiple) | B4: =EBITDA_Bridge!G6*Key_Assumptions!B38
A5: PV of TV (Gordon) | B5: =B2/(1+WACC!B15)^IF(Key_Assumptions!B45=1,5,5)
A6: PV of TV (Exit Multiple) | B6: =B3/(1+WACC!B15)^IF(Key_Assumptions!B45=1,5,5)

Sheet EV_Equity_Bridge
A1: EV to Equity Bridge
A3: Enterprise Value (Gordon) | B3: =DCF_Valuation!B15
A4: Less: Net Debt | B4: =-Key_Assumptions!B41
A5: Equity Value | B5: =B3+B4
A6: Implied Share Price | B6: =B5/Key_Assumptions!B42

Sheet Sensitivity
A1: Sensitivity Analysis
A3: SHARE PRICE: WACC vs TERMINAL GROWTH (Gordon Growth)
A5: Terminal Growth → | B5: WACC ↓ | C5: 0.015 | D5: 0.02 | E5: 0.025 | F5: 0.03 | G5: 0.035
B6: 0.08 | C6: — | D6: — | E6: — | F6: — | G6: —
B7: 0.09 | C7: — | D7: — | E7: — | F7: — | G7: —
B8: 0.1 | C8: — | D8: — | E8: — | F8: — | G8: —
B9: 0.11 | C9: — | D9: — | E9: — | F9: — | G9: —
B10: 0.12 | C10: — | D10: — | E10: — | F10: — | G10: —
A13: Note: Populate data table manually or via VBA
A15: SHARE PRICE: WACC vs EXIT MULTIPLE
A17: Exit Multiple → | B17: WACC ↓ | C17: 8 | D17: 9 | E17: 10 | F17: 11 | G17: 12
B18: 0.08 | C18: — | D18: — | E18: — | F18: — | G18: —
B19: 0.09 | C19: — | D19: — | E19: — | F19: — | G19: —
B20: 0.1 | C20: — | D20: — | E20: — | F20: — | G20: —
B21: 0.11 | C21: — | D21: — | E21: — | F21: — | G21: —
B22: 0.12 | C22: — | D22: — | E22: — | F22: — | G22: —

Sheet Scenario_Manager
A1: Scenario Manager
A3: DEAL CASE (REALISTIC CABLE TARGET)
A4: Buyer | B4: Comcast (CMCSA)
A5: Target | B5: Altice USA (ATUS)
A6: Deal Type | B6: Strategic Acquisition
A7: Purchase Premium | B7: 0.3
A8: LTM EV/EBITDA Multiple | B8: 7.5
A9: Synergies (Run-Rate, $M) | B9: 300
A10: Funding Mix (Debt / Equity) | B10: 60% / 40%

Sheet KPI_Dashboard
A1: KPI Dashboard
A3: Implied Share Price (Gordon) | B3: =DCF_Valuation!B18
A4: Implied Share Price (Exit) | B4: =DCF_Valuation!B24

Sheet Trading_Comps
A1: Trading Comps
A3: (Placeholder for trading comps)

Sheet Transactions_Comps
A1: Transactions Comps
A3: (Placeholder for transactions comps)

Sheet Charts_Checks
A1: Charts & Model Integrity Checks
A3: VALIDATION CHECKS
A4: Check | B4: Status | C4: Description
A5: WACC > Terminal Growth | B5: =IF(WACC!B15>Key_Assumptions!B37,"PASS","FAIL") | C5: Terminal growth must be less than WACC
A6: WACC is Reasonable (5-15%) | B6: =IF(AND(WACC!B15>=0.05,WACC!B15<=0.15),"PASS","WARNING") | C6: WACC typically ranges 5-15%
A7: Terminal Growth ≤ 4% | B7: =IF(Key_Assumptions!B37<=0.04,"PASS","WARNING") | C7: Should not exceed long-term GDP growth
A8: Positive Base Revenue | B8: =IF(Key_Assumptions!B8>0,"PASS","FAIL") | C8: Revenue must be positive
A9: Shares Outstanding > 0 | B9: =IF(Key_Assumptions!B42>0,"PASS","FAIL") | C9: Shares must be positive
