Workbook

Sheet Assumptions
A1: DCF Valuation Model - MICROSOFT CORPORATION (MSFT)
A3: COMPANY INFORMATION
A4: Company Name | B4: MICROSOFT CORPORATION
A5: Ticker | B5: MSFT
A7: REVENUE ASSUMPTIONS
A8: Base Year Revenue ($M) | B8: 281724
A9: Year 1 Growth | B9: 0.1
A10: Year 2 Growth | B10: 0.08
A11: Year 3 Growth | B11: 0.06
A12: Year 4 Growth | B12: 0.05
A13: Year 5 Growth | B13: 0.04
A15: OPERATING ASSUMPTIONS
A16: EBITDA Margin | B16: 0.45
A17: D&A (% of Revenue) | B17: 0.03
A18: CapEx (% of Revenue) | B18: 0.04
A19: NWC (% of Revenue) | B19: 0.1
A20: Tax Rate | B20: 0.25
A22: WACC BUILDUP
A23: Risk-Free Rate | B23: 0.045
A24: Equity Risk Premium | B24: 0.055
A25: Levered Beta | B25: 1
A26: Pre-Tax Cost of Debt | B26: 0.05
A27: Debt / Total Capital | B27: 0.2
A29: Cost of Equity (CAPM) | B29: =B23+B25*B24
A30: After-Tax Cost of Debt | B30: =B26*(1-B20)
A31: WACC | B31: =B29*(1-B27)+B30*B27
A33: TERMINAL VALUE ASSUMPTIONS
A34: Perpetuity Growth Rate | B34: 0.025
A35: Exit EV/EBITDA Multiple | B35: 12
A37: CAPITAL STRUCTURE
A38: Net Debt ($M) | B38: 14695
A39: Shares Outstanding (M) | B39: 7464
A41: MODEL SETTINGS
A42: Use Mid-Year Convention | B42: 1 | C42: (1=Yes, 0=No)

Sheet DCF Analysis
A1: Discounted Cash Flow Analysis
B3: Base | C3: Year 1 | D3: Year 2 | E3: Year 3 | F3: Year 4 | G3: Year 5 | H3: Terminal
A4: Revenue Growth | B4: — | C4: =Assumptions!B9 | D4: =Assumptions!B10 | E4: =Assumptions!B11 | F4: =Assumptions!B12 | G4: =Assumptions!B13
A5: Revenue | B5: =Assumptions!B8 | C5: =B5*(1+C4) | D5: =C5*(1+D4) | E5: =D5*(1+E4) | F5: =E5*(1+F4) | G5: =F5*(1+G4)
A6: EBITDA | B6: =B5*Assumptions!B16 | C6: =C5*Assumptions!B16 | D6: =D5*Assumptions!B16 | E6: =E5*Assumptions!B16 | F6: =F5*Assumptions!B16 | G6: =G5*Assumptions!B16
A7: Less: D&A | B7: =-B5*Assumptions!B17 | C7: =-C5*Assumptions!B17 | D7: =-D5*Assumptions!B17 | E7: =-E5*Assumptions!B17 | F7: =-F5*Assumptions!B17 | G7: =-G5*Assumptions!B17
A8: EBIT | B8: =B6+B7 | C8: =C6+C7 | D8: =D6+D7 | E8: =E6+E7 | F8: =F6+F7 | G8: =G6+G7
A9: Less: Taxes | B9: =-MAX(0,B8)*Assumptions!B20 | C9: =-MAX(0,C8)*Assumptions!B20 | D9: =-MAX(0,D8)*Assumptions!B20 | E9: =-MAX(0,E8)*Assumptions!B20 | F9: =-MAX(0,F8)*Assumptions!B20 | G9: =-MAX(0,G8)*Assumptions!B20
A10: NOPAT | B10: =B8+B9 | C10: =C8+C9 | D10: =D8+D9 | E10: =E8+E9 | F10: =F8+F9 | G10: =G8+G9
A11: Plus: D&A | B11: =-B7 | C11: =-C7 | D11: =-D7 | E11: =-E7 | F11: =-F7 | G11: =-G7
A12: Less: CapEx | B12: =-B5*Assumptions!B18 | C12: =-C5*Assumptions!B18 | D12: =-D5*Assumptions!B18 | E12: =-E5*Assumptions!B18 | F12: =-F5*Assumptions!B18 | G12: =-G5*Assumptions!B18
A13: Less: Chg in NWC | B13: 0 | C13: =-(C5-B5)*Assumptions!B19 | D13: =-(D5-C5)*Assumptions!B19 | E13: =-(E5-D5)*Assumptions!B19 | F13: =-(F5-E5)*Assumptions!B19 | G13: =-(G5-F5)*Assumptions!B19
A14: Unlevered FCF | B14: =B10+B11+B12+B13 | C14: =C10+C11+C12+C13 | D14: =D10+D11+D12+D13 | E14: =E10+E11+E12+E13 | F14: =F10+F11+F12+F13 | G14: =G10+G11+G12+G13
A16: PRESENT VALUE CALCULATION
A17: Discount Period | C17: =IF(Assumptions!B42=1,0+0.5,1) | D17: =IF(Assumptions!B42=1,1+0.5,2) | E17: =IF(Assumptions!B42=1,2+0.5,3) | F17: =IF(Assumptions!B42=1,3+0.5,4) | G17: =IF(Assumptions!B42=1,4+0.5,5)
A18: Discount Factor | C18: =1/(1+Assumptions!B31)^C17 | D18: =1/(1+Assumptions!B31)^D17 | E18: =1/(1+Assumptions!B31)^E17 | F18: =1/(1+Assumptions!B31)^F17 | G18: =1/(1+Assumptions!B31)^G17
A19: PV of FCF | C19: =C14*C18 | D19: =D14*D18 | E19: =E14*E18 | F19: =F14*F18 | G19: =G14*G18
A21: TERMINAL VALUE
A22: Terminal Value (Gordon Growth) | B22: =G14*(1+Assumptions!B34)/(Assumptions!B31-Assumptions!B34)
A23: Terminal Value (Exit Multiple) | B23: =G6*Assumptions!B35
A24: PV of TV (Gordon Growth) | B24: =B22/(1+Assumptions!B31)^IF(Assumptions!B42=1,5,5)
A25: PV of TV (Exit Multiple) | B25: =B23/(1+Assumptions!B31)^IF(Assumptions!B42=1,5,5)
A27: VALUATION SUMMARY
A28: Sum of PV of FCFs | B28: =SUM(C19:G19)
A30: GORDON GROWTH METHOD
A31: Enterprise Value | B31: =B28+B24
A32: Less: Net Debt | B32: =-Assumptions!B38
A33: Equity Value | B33: =B31+B32
A34: Implied Share Price | B34: =B33/Assumptions!B39
A36: EXIT MULTIPLE METHOD
A37: Enterprise Value | B37: =B28+B25
A38: Less: Net Debt | B38: =-Assumptions!B38
A39: Equity Value | B39: =B37+B38
A40: Implied Share Price | B40: =B39/Assumptions!B39

Sheet Sensitivity
A1: Sensitivity Analysis
A3: SHARE PRICE: WACC vs TERMINAL GROWTH (Gordon Growth)
A5: Terminal Growth → | B5: WACC ↓ | C5: 0.015 | D5: 0.02 | E5: 0.025 | F5: 0.03 | G5: 0.035
B6: 0.08 | C6: — | D6: — | E6: — | F6: — | G6: —
B7: 0.09 | C7: — | D7: — | E7: — | F7: — | G7: —
B8: 0.1 | C8: — | D8: — | E8: — | F8: — | G8: —
B9: 0.11 | C9: — | D9: — | E9: — | F9: — | G9: —
B10: 0.12 | C10: — | D10: — | E10: — | F10: — | G10: —
A13: Note: Populate data table manually or via VBA
A15: SHARE PRICE: WACC vs EXIT MULTIPLE
A17: Exit Multiple → | B17: WACC ↓ | C17: 8 | D17: 9 | E17: 10 | F17: 11 | G17: 12
B18: 0.08 | C18: — | D18: — | E18: — | F18: — | G18: —
B19: 0.09 | C19: — | D19: — | E19: — | F19: — | G19: —
B20: 0.1 | C20: — | D20: — | E20: — | F20: — | G20: —
B21: 0.11 | C21: — | D21: — | E21: — | F21: — | G21: —
B22: 0.12 | C22: — | D22: — | E22: — | F22: — | G22: —

Sheet Checks
A1: Model Integrity Checks
A3: VALIDATION CHECKS
A4: Check | B4: Status | C4: Description
A5: WACC > Terminal Growth | B5: =IF(Assumptions!B31>Assumptions!B34,"PASS","FAIL") | C5: Terminal growth must be less than WACC
A6: WACC is Reasonable (5-15%) | B6: =IF(AND(Assumptions!B31>=0.05,Assumptions!B31<=0.15),"PASS","WARNING") | C6: WACC typically ranges 5-15%
A7: Terminal Growth ≤ 4% | B7: =IF(Assumptions!B34<=0.04,"PASS","WARNING") | C7: Should not exceed long-term GDP growth
A8: Positive Base Revenue | B8: =IF(Assumptions!B8>0,"PASS","FAIL") | C8: Revenue must be positive
A9: Shares Outstanding > 0 | B9: =IF(Assumptions!B39>0,"PASS","FAIL") | C9: Shares must be positive
